bytedance_fpng/__init__.py
bytedance_fpng-0.0.1.dist-info/METADATA
bytedance_fpng-0.0.1.dist-info/WHEEL
bytedance_fpng-0.0.1.dist-info/top_level.txt
bytedance_fpng-0.0.1.dist-info/RECORD
