Metadata-Version: 2.1
Name: bytedance-fpng
Version: 0.0.1
Summary: A simple package named bytedance_fpng
Home-page: https://github.com/artifact/bytedance_fpng.git
Author: artifact
Author-email: artifact@example.com
License: UNKNOWN
Platform: UNKNOWN
Classifier: Programming Language :: Python :: 3
Classifier: License :: OSI Approved :: MIT License
Classifier: Operating System :: OS Independent
